{"items": [{"provincia": "zaragoza", "tipo": "CPRI", "solicitudes": 26, "coord": "41.639364, -0.87296", "oferta": 44, "diferencia": 18, "label": "CPRI AGUST\u00cdN GERIC\u00d3 (ZARAGOZA)", "estado": true}, {"provincia": "zaragoza", "tipo": "CEIP", "solicitudes": 43, "coord": "41.687976, -0.873452", "oferta": 63, "diferencia": 20, "label": "CEIP AGUSTINA DE ARAG\u00d3N (ZARAGOZA)", "estado": true}, {"provincia": "zaragoza", "tipo": "CEIP", "solicitudes": 53, "coord": "41.232527, -0.046279", "oferta": 63, "diferencia": 10, "label": "CEIP ALEJO LOR\u00c9N ALBAREDA (CASPE)", "estado": true}, {"provincia": "zaragoza", "tipo": "CEIP", "solicitudes": 21, "coord": "41.654605, -0.911007", "oferta": 44, "diferencia": 23, "label": "CEIP ANA MAYAYO (ZARAGOZA)", "estado": true}, {"provincia": "zaragoza", "tipo": "CEIP", "solicitudes": 10, "coord": "41.647949, -0.904047", "oferta": 22, "diferencia": 12, "label": "CEIP ANDR\u00c9S MANJ\u00d3N (ZARAGOZA)", "estado": true}, {"provincia": "zaragoza", "tipo": "CEIP", "solicitudes": 24, "coord": "41.716265, -0.842306", "oferta": 42, "diferencia": 18, "label": "CEIP ANDR\u00c9S OLIV\u00c1N (SAN JUAN DE MOZARRIFAR)", "estado": true}, {"provincia": "zaragoza", "tipo": "CEIP", "solicitudes": 10, "coord": "41.60764, -0.824234", "oferta": 22, "diferencia": 12, "label": "CEIP \u00c1NGEL ESCORIAZA (CARTUJA BAJA)", "estado": true}, {"provincia": "zaragoza", "tipo": "CEIP", "solicitudes": 7, "coord": "41.645419, -0.9159", "oferta": 22, "diferencia": 15, "label": "CEIP ANTONIO BELTR\u00c1N MART\u00cdNEZ (ZARAGOZA)", "estado": true}, {"provincia": "zaragoza", "tipo": "CPRI", "solicitudes": 22, "coord": "41.678919,-0.963227", "oferta": 22, "diferencia": 0, "label": "CPRI ANTONIO MACHADO (VENTA DEL OLIVAR)", "estado": true}, {"provincia": "zaragoza", "tipo": "CEIP", "solicitudes": 14, "coord": "41.724808, -1.034265", "oferta": 22, "diferencia": 8, "label": "CEIP ANTONIO MART\u00cdNEZ GARAY (CASETAS)", "estado": true}, {"provincia": "zaragoza", "tipo": "CEIP", "solicitudes": 34, "coord": "41.769761, -1.1271", "oferta": 42, "diferencia": 8, "label": "CEIP ARAG\u00d3N (ALAGON)", "estado": true}, {"provincia": "zaragoza", "tipo": "CEIP", "solicitudes": 49, "coord": "41.625328,-0.957231", "oferta": 100, "diferencia": 51, "label": "CEIP ARCOSUR (ZARAGOZA)", "estado": true}, {"provincia": "zaragoza", "tipo": "CEIP", "solicitudes": 44, "coord": "41.351285, -1.649232", "oferta": 42, "diferencia": -2, "label": "CEIP AUGUSTA B\u00cdLBILIS (CALATAYUD)", "estado": false}, {"provincia": "zaragoza", "tipo": "CPRI", "solicitudes": 67, "coord": "41.638845, -0.863349", "oferta": 44, "diferencia": -23, "label": "CPRI BAJO ARAG\u00d3N (ZARAGOZA)", "estado": false}, {"provincia": "zaragoza", "tipo": "CEIP", "solicitudes": 11, "coord": "41.331339, -1.645686", "oferta": 21, "diferencia": 10, "label": "CEIP BALTASAR GRACI\u00c1N (CALATAYUD)", "estado": true}, {"provincia": "zaragoza", "tipo": "CEIP", "solicitudes": 30, "coord": "41.638406, -0.893881", "oferta": 25, "diferencia": -5, "label": "CEIP BASILIO PARA\u00cdSO (ZARAGOZA)", "estado": false}, {"provincia": "zaragoza", "tipo": "CPRI", "solicitudes": 10, "coord": "41.639175, -0.888499", "oferta": 25, "diferencia": 15, "label": "CPRI CALASANCIO (ZARAGOZA)", "estado": true}, {"provincia": "zaragoza", "tipo": "CPRI", "solicitudes": 47, "coord": "41.652952, -0.883361", "oferta": 50, "diferencia": 3, "label": "CPRI CALASANZ (ZARAGOZA)", "estado": true}, {"provincia": "zaragoza", "tipo": "CEIP", "solicitudes": 13, "coord": "41.635883, -0.870849", "oferta": 44, "diferencia": 31, "label": "CEIP CALIXTO ARI\u00d1O-HILARIO VAL (ZARAGOZA)", "estado": true}, {"provincia": "zaragoza", "tipo": "CEIP", "solicitudes": 32, "coord": "41.832123, -1.533911", "oferta": 42, "diferencia": 10, "label": "CEIP CAMPO DE BORJA (BORJA)", "estado": true}, {"provincia": "zaragoza", "tipo": "CEIP", "solicitudes": 39, "coord": "41.659058, -0.873593", "oferta": 44, "diferencia": 5, "label": "CEIP C\u00c1NDIDO DOMINGO (ZARAGOZA)", "estado": true}, {"provincia": "zaragoza", "tipo": "CPRI", "solicitudes": 10, "coord": "41.648005, -0.878017", "oferta": 25, "diferencia": 15, "label": "CPRI CANT\u00cdN Y GAMBOA (ZARAGOZA)", "estado": true}, {"provincia": "zaragoza", "tipo": "CPRI", "solicitudes": 38, "coord": "41.642049, -0.895452", "oferta": 50, "diferencia": 12, "label": "CPRI CARDENAL XAVIERRE (ZARAGOZA)", "estado": true}, {"provincia": "zaragoza", "tipo": "CEIP", "solicitudes": 85, "coord": "41.689086, -0.878708", "oferta": 84, "diferencia": -1, "label": "CEIP CATALINA DE ARAG\u00d3N (ZARAGOZA)", "estado": false}, {"provincia": "zaragoza", "tipo": "CEIP", "solicitudes": 52, "coord": "42.125369, -1.137168", "oferta": 42, "diferencia": -10, "label": "CEIP CERVANTES (EJEA DE LOS CABALLEROS)", "estado": false}, {"provincia": "zaragoza", "tipo": "CEIP", "solicitudes": 57, "coord": "41.636817, -0.906248", "oferta": 75, "diferencia": 18, "label": "CEIP C\u00c9SAR AUGUSTO (ZARAGOZA)", "estado": true}, {"provincia": "zaragoza", "tipo": "CEIP", "solicitudes": 67, "coord": "41.637709, -0.905329", "oferta": 75, "diferencia": 8, "label": "CEIP CES\u00c1REO ALIERTA (ZARAGOZA)", "estado": true}, {"provincia": "zaragoza", "tipo": "CEIP", "solicitudes": 25, "coord": "41.647978, -0.914962", "oferta": 44, "diferencia": 19, "label": "CEIP CIUDAD DE ZARAGOZA (ZARAGOZA)", "estado": true}, {"provincia": "zaragoza", "tipo": "CPRI", "solicitudes": 59, "coord": "41.644913, -0.889077", "oferta": 50, "diferencia": -9, "label": "CPRI COLEGIO MONTESSORI (ZARAGOZA)", "estado": false}, {"provincia": "zaragoza", "tipo": "CPRI", "solicitudes": 94, "coord": "41.649646, -0.886266", "oferta": 75, "diferencia": -19, "label": "CPRI COMPA\u00d1\u00cdA DE MAR\u00cdA (ZARAGOZA)", "estado": false}, {"provincia": "zaragoza", "tipo": "CEIP", "solicitudes": 20, "coord": "41.235478, -0.037394", "oferta": 21, "diferencia": 1, "label": "CEIP COMPROMISO DE CASPE (CASPE)", "estado": true}, {"provincia": "zaragoza", "tipo": "CPRI", "solicitudes": 48, "coord": "41.678429,-0.965013", "oferta": 44, "diferencia": -4, "label": "CPRI CONDES DE ARAG\u00d3N (VENTA DEL OLIVAR)", "estado": false}, {"provincia": "zaragoza", "tipo": "CEIP", "solicitudes": 39, "coord": "41.664912, -0.881467", "oferta": 63, "diferencia": 24, "label": "CEIP CORTES DE ARAG\u00d3N (ZARAGOZA)", "estado": true}, {"provincia": "zaragoza", "tipo": "CPRI", "solicitudes": 77, "coord": "41.686745,-0.868839", "oferta": 84, "diferencia": 7, "label": "CPRI CRISTO REY (ZARAGOZA)", "estado": true}, {"provincia": "zaragoza", "tipo": "CEIP", "solicitudes": 36, "coord": "41.5855, -0.945038", "oferta": 100, "diferencia": 64, "label": "CEIP CUARTE DE HUERVA III (CUARTE DE HUERVA)", "estado": true}, {"provincia": "zaragoza", "tipo": "CEIP", "solicitudes": 78, "coord": "41.637709, -0.905329", "oferta": 75, "diferencia": -3, "label": "CEIP DOCTOR AZ\u00daA (ZARAGOZA)", "estado": false}, {"provincia": "zaragoza", "tipo": "CEIP", "solicitudes": 16, "coord": "41.627021, -0.890401", "oferta": 25, "diferencia": 9, "label": "CEIP DOMINGO MIRAL (ZARAGOZA)", "estado": true}, {"provincia": "zaragoza", "tipo": "CPRI", "solicitudes": 18, "coord": "41.657441, -0.855479", "oferta": 22, "diferencia": 4, "label": "CPRI DON BOSCO (ZARAGOZA)", "estado": true}, {"provincia": "zaragoza", "tipo": "CPRI", "solicitudes": 43, "coord": "41.629999, -0.881727", "oferta": 50, "diferencia": 7, "label": "CPRI EL BUEN PASTOR (ZARAGOZA)", "estado": true}, {"provincia": "zaragoza", "tipo": "CEIP", "solicitudes": 30, "coord": "41.669392, -0.822729", "oferta": 66, "diferencia": 36, "label": "CEIP EL ESPARTIDERO (ZARAGOZA)", "estado": true}, {"provincia": "zaragoza", "tipo": "CPRI", "solicitudes": 76, "coord": "41.668708, -0.882163", "oferta": 63, "diferencia": -13, "label": "CPRI EL PILAR-MARISTAS (ZARAGOZA)", "estado": false}, {"provincia": "zaragoza", "tipo": "CPRI", "solicitudes": 122, "coord": "41.632087, -0.900363", "oferta": 125, "diferencia": 3, "label": "CPRI EL SALVADOR (ZARAGOZA)", "estado": true}, {"provincia": "zaragoza", "tipo": "CEIP", "solicitudes": 59, "coord": "41.635884, -0.905461", "oferta": 75, "diferencia": 16, "label": "CEIP ELISEO GODOY BELTR\u00c1N (ZARAGOZA)", "estado": true}, {"provincia": "zaragoza", "tipo": "CEIP", "solicitudes": 11, "coord": "41.653328, -0.90401", "oferta": 22, "diferencia": 11, "label": "CEIP EMILIO MORENO CALVETE (ZARAGOZA)", "estado": true}, {"provincia": "zaragoza", "tipo": "CPRI", "solicitudes": 70, "coord": "41.654774, -0.885996", "oferta": 63, "diferencia": -7, "label": "CPRI ESCUELAS P\u00cdAS (ZARAGOZA)", "estado": false}, {"provincia": "zaragoza", "tipo": "CPRI", "solicitudes": 15, "coord": "41.633515, -0.871056", "oferta": 22, "diferencia": 7, "label": "CPRI ESCUELAS P\u00cdAS DE SANTA ENGRACIA (ZARAGOZA)", "estado": true}, {"provincia": "zaragoza", "tipo": "CEIP", "solicitudes": 48, "coord": "41.664858, -0.873879", "oferta": 63, "diferencia": 15, "label": "CEIP EUGENIO L\u00d3PEZ Y L\u00d3PEZ (ZARAGOZA)", "estado": true}, {"provincia": "zaragoza", "tipo": "CEIP", "solicitudes": 12, "coord": "41.700386, -0.971411", "oferta": 22, "diferencia": 10, "label": "CEIP FERN\u00c1NDEZ VIZARRA (MONZALBARBA)", "estado": true}, {"provincia": "zaragoza", "tipo": "CEIP", "solicitudes": 9, "coord": "41.651042, -0.927683", "oferta": 22, "diferencia": 13, "label": "CEIP FERNANDO EL CAT\u00d3LICO (ZARAGOZA)", "estado": true}, {"provincia": "zaragoza", "tipo": "CEIP", "solicitudes": 15, "coord": "42.131292, -1.311907", "oferta": 21, "diferencia": 6, "label": "CEIP FERRER Y RACAJ (EJEA DE LOS CABALLEROS)", "estado": true}, {"provincia": "zaragoza", "tipo": "CEIP", "solicitudes": 12, "coord": "41.758977, -0.797703", "oferta": 22, "diferencia": 10, "label": "CEIP FLORENCIO JARDIEL (PE\u00d1AFLOR)", "estado": true}, {"provincia": "zaragoza", "tipo": "CEIP", "solicitudes": 38, "oferta": 21, "diferencia": -17, "label": "CEIP FLORI\u00c1N REY (ALMUNIA DE DO\u00d1A GODINA (LA))", "estado": false}, {"provincia": "zaragoza", "tipo": "CEIP", "solicitudes": 64, "coord": "41.585459, -0.945038", "oferta": 75, "diferencia": 11, "label": "CEIP FORO ROMANO (CUARTE DE HUERVA)", "estado": true}, {"provincia": "zaragoza", "tipo": "CEIP", "solicitudes": 39, "coord": "41.348936, -1.637906", "oferta": 30, "diferencia": -9, "label": "CEIP FRANCISCO DE GOYA (CALATAYUD)", "estado": false}, {"provincia": "zaragoza", "tipo": "CEIP", "solicitudes": 12, "coord": "41.649461, -0.877964", "oferta": 25, "diferencia": 13, "label": "CEIP GASC\u00d3N Y MAR\u00cdN (ZARAGOZA)", "estado": true}, {"provincia": "zaragoza", "tipo": "CEIP", "solicitudes": 3, "coord": "41.668796, -0.843652", "oferta": 22, "diferencia": 19, "label": "CEIP GLORIA ARENILLAS (ZARAGOZA)", "estado": true}, {"provincia": "zaragoza", "tipo": "CEIP", "solicitudes": 73, "coord": "41.670653, -0.828975", "oferta": 66, "diferencia": -7, "label": "CEIP GUILLERMO FAT\u00c1S (ZARAGOZA)", "estado": false}, {"provincia": "zaragoza", "tipo": "CEIP", "solicitudes": 19, "coord": "41.683263, -1.024039", "oferta": 44, "diferencia": 25, "label": "CEIP GUSTAVO ADOLFO B\u00c9CQUER (GARRAPINILLOS)", "estado": true}, {"provincia": "zaragoza", "tipo": "CEIP", "solicitudes": 15, "coord": "41.683147, -0.825782", "oferta": 22, "diferencia": 7, "label": "CEIP HERMANOS ARGENSOLA (MONTA\u00d1ANA)", "estado": true}, {"provincia": "zaragoza", "tipo": "CEIP", "solicitudes": 20, "coord": "41.677423, -0.883092", "oferta": 63, "diferencia": 43, "label": "CEIP HERMANOS MARX (ZARAGOZA)", "estado": true}, {"provincia": "zaragoza", "tipo": "CPRI", "solicitudes": 90, "coord": "41.649043, -0.901198", "oferta": 66, "diferencia": -24, "label": "CPRI HIJAS DE SAN JOS\u00c9 (ZARAGOZA)", "estado": false}, {"provincia": "zaragoza", "tipo": "CEIP", "solicitudes": 75, "coord": "41.659258, -0.867356", "oferta": 66, "diferencia": -9, "label": "CEIP HILARI\u00d3N GIMENO (ZARAGOZA)", "estado": false}, {"provincia": "zaragoza", "tipo": "CEIP", "solicitudes": 28, "coord": "41.64604, -0.921774", "oferta": 44, "diferencia": 16, "label": "CEIP HISPANIDAD (ZARAGOZA)", "estado": true}, {"provincia": "zaragoza", "tipo": "CEIP", "solicitudes": 27, "coord": "41.713175, -1.022299", "oferta": 22, "diferencia": -5, "label": "CEIP INFANTA ELENA (UTEBO)", "estado": false}, {"provincia": "zaragoza", "tipo": "CPRI", "solicitudes": 25, "coord": "41.646592, -0.874974", "oferta": 25, "diferencia": 0, "label": "CPRI INMACULADA CONCEPCI\u00d3N (ZARAGOZA)", "estado": true}, {"provincia": "zaragoza", "tipo": "CPRI", "solicitudes": 53, "coord": "41.58378, -0.95127", "oferta": 25, "diferencia": -28, "label": "CPRI INTERNACIONAL \u00c1NFORA (CUARTE DE HUERVA)", "estado": false}, {"provincia": "zaragoza", "tipo": "CEIP", "solicitudes": 62, "coord": "41.640942, -0.931356", "oferta": 66, "diferencia": 4, "label": "CEIP JER\u00d3NIMO BLANCAS Y TOM\u00c1S (ZARAGOZA)", "estado": true}, {"provincia": "zaragoza", "tipo": "CEIP", "solicitudes": 13, "coord": "41.664004, -0.899412", "oferta": 42, "diferencia": 29, "label": "CEIP JER\u00d3NIMO ZURITA Y CASTRO (ZARAGOZA)", "estado": true}, {"provincia": "zaragoza", "tipo": "CEIP", "solicitudes": 29, "coord": "41.906537, -1.725464", "oferta": 21, "diferencia": -8, "label": "CEIP JOAQU\u00cdN COSTA (TARAZONA)", "estado": false}, {"provincia": "zaragoza", "tipo": "CEIP", "solicitudes": 36, "coord": "41.651654, -0.891969", "oferta": 50, "diferencia": 14, "label": "CEIP JOAQU\u00cdN COSTA (ZARAGOZA)", "estado": true}, {"provincia": "zaragoza", "tipo": "CEIP", "solicitudes": 24, "coord": "41.677622, -0.897084", "oferta": 42, "diferencia": 18, "label": "CEIP JOS\u00c9 ANTONIO LABORDETA SUB\u00cdAS (ZARAGOZA)", "estado": true}, {"provincia": "zaragoza", "tipo": "CEIP", "solicitudes": 31, "coord": "41.657499, -0.916725", "oferta": 66, "diferencia": 35, "label": "CEIP JOS\u00c9 CAM\u00d3N AZNAR (ZARAGOZA)", "estado": true}, {"provincia": "zaragoza", "tipo": "CEIP", "solicitudes": 44, "coord": "41.647398, -0.906161", "oferta": 44, "diferencia": 0, "label": "CEIP JOS\u00c9 MAR\u00cdA MIR (ZARAGOZA)", "estado": true}, {"provincia": "zaragoza", "tipo": "CEIP", "solicitudes": 40, "coord": "41.674533, -0.88304", "oferta": 63, "diferencia": 23, "label": "CEIP JOSEFA AMAR Y BORB\u00d3N (ZARAGOZA)", "estado": true}, {"provincia": "zaragoza", "tipo": "CEIP", "solicitudes": 22, "coord": "41.668399, -0.839133", "oferta": 44, "diferencia": 22, "label": "CEIP JUAN PABLO BONET (MOVERA)", "estado": true}, {"provincia": "zaragoza", "tipo": "CEIP", "solicitudes": 34, "coord": "41.65547, -0.89942", "oferta": 44, "diferencia": 10, "label": "CEIP JUAN XXIII (ZARAGOZA)", "estado": true}, {"provincia": "zaragoza", "tipo": "CEIP", "solicitudes": 49, "coord": "41.65941, -0.943783", "oferta": 44, "diferencia": -5, "label": "CEIP JULI\u00c1N NIETO TAPIA (ZARAGOZA)", "estado": false}, {"provincia": "zaragoza", "tipo": "CEIP", "solicitudes": 7, "coord": "41.647264, -0.865093", "oferta": 22, "diferencia": 15, "label": "CEIP JULI\u00c1N SANZ IB\u00c1\u00d1EZ (ZARAGOZA)", "estado": true}, {"provincia": "zaragoza", "tipo": "CEIP", "solicitudes": 74, "coord": "41.657422, -0.92411", "oferta": 66, "diferencia": -8, "label": "CEIP JULIO VERNE (ZARAGOZA)", "estado": false}, {"provincia": "zaragoza", "tipo": "CEIP", "solicitudes": 67, "coord": "41.662678, -0.902709", "oferta": 42, "diferencia": -25, "label": "CEIP LA ALMOZARA (ZARAGOZA)", "estado": false}, {"provincia": "zaragoza", "tipo": "CPRI", "solicitudes": 23, "coord": "41.656756, -0.891298", "oferta": 42, "diferencia": 19, "label": "CPRI LA ANUNCIATA (ZARAGOZA)", "estado": true}, {"provincia": "zaragoza", "tipo": "CPRI", "solicitudes": 16, "coord": "41.668991, -0.829976", "oferta": 22, "diferencia": 6, "label": "CPRI LA CONCEPCI\u00d3N (ZARAGOZA)", "estado": true}, {"provincia": "zaragoza", "tipo": "CEIP", "solicitudes": 42, "coord": "41.663407, -0.858024", "oferta": 66, "diferencia": 24, "label": "CEIP LA ESTRELLA (ZARAGOZA)", "estado": true}, {"provincia": "zaragoza", "tipo": "CEIP", "solicitudes": 27, "coord": "41.660183, -0.858322", "oferta": 44, "diferencia": 17, "label": "CEIP LA JOTA (ZARAGOZA)", "estado": true}, {"provincia": "zaragoza", "tipo": "CPRI", "solicitudes": 11, "coord": "41.635058, -0.88616", "oferta": 25, "diferencia": 14, "label": "CPRI LA MILAGROSA (ZARAGOZA)", "estado": true}, {"provincia": "zaragoza", "tipo": "CEIP", "solicitudes": 9, "coord": "41.61922, -0.78352", "oferta": 22, "diferencia": 13, "label": "CEIP LA PORTALADA (PASTRIZ)", "estado": true}, {"provincia": "zaragoza", "tipo": "CPRI", "solicitudes": 16, "coord": "41.657869, -0.867757", "oferta": 22, "diferencia": 6, "label": "CPRI LA PUR\u00cdSIMA Y SAN ANTONIO (ZARAGOZA)", "estado": true}, {"provincia": "zaragoza", "tipo": "CPRI", "solicitudes": 75, "coord": "41.639713, -0.894478", "oferta": 75, "diferencia": 0, "label": "CPRI LA SALLE FRANCISCANAS (ZARAGOZA)", "estado": true}, {"provincia": "zaragoza", "tipo": "CPRI", "solicitudes": 81, "coord": "41.637115, -0.870835", "oferta": 66, "diferencia": -15, "label": "CPRI LA SALLE MONTEMOL\u00cdN (ZARAGOZA)", "estado": false}, {"provincia": "zaragoza", "tipo": "CEIP", "solicitudes": 47, "coord": "41.648712, -0.864709", "oferta": 66, "diferencia": 19, "label": "CEIP LAS FUENTES (ZARAGOZA)", "estado": true}, {"provincia": "zaragoza", "tipo": "CEIP", "solicitudes": 56, "coord": "41.632722, -0.749485", "oferta": 42, "diferencia": -14, "label": "CEIP LOS ALBARES (PUEBLA DE ALFINDEN (LA))", "estado": false}, {"provincia": "zaragoza", "tipo": "CEIP", "solicitudes": 55, "coord": "41.670992, -0.874558", "oferta": 63, "diferencia": 8, "label": "CEIP LUCIEN BRIET (ZARAGOZA)", "estado": true}, {"provincia": "zaragoza", "tipo": "CEIP", "solicitudes": 6, "coord": "41.632126, -0.88737", "oferta": 25, "diferencia": 19, "label": "CEIP LUIS VIVES (ZARAGOZA)", "estado": true}, {"provincia": "zaragoza", "tipo": "CPRI", "solicitudes": 71, "coord": "41.627839, -0.906287", "oferta": 75, "diferencia": 4, "label": "CPRI MADRE MAR\u00cdA ROSA MOLAS (ZARAGOZA)", "estado": true}, {"provincia": "zaragoza", "tipo": "CEIP", "solicitudes": 13, "coord": "41.649988, -0.821923", "oferta": 22, "diferencia": 9, "label": "CEIP MAESTRO DON PEDRO OR\u00d3S (MOVERA)", "estado": true}, {"provincia": "zaragoza", "tipo": "CEIP", "solicitudes": 11, "coord": "41.643667, -0.865242", "oferta": 44, "diferencia": 33, "label": "CEIP MARCOS FRECH\u00cdN (ZARAGOZA)", "estado": true}, {"provincia": "zaragoza", "tipo": "CPRI", "solicitudes": 31, "coord": "41.636003, -0.880405", "oferta": 44, "diferencia": 13, "label": "CPRI MAR\u00cdA AUXILIADORA (ZARAGOZA)", "estado": true}, {"provincia": "zaragoza", "tipo": "CPRI", "solicitudes": 47, "coord": "41.651055, -0.919927", "oferta": 44, "diferencia": -3, "label": "CPRI MAR\u00cdA INMACULADA (ZARAGOZA)", "estado": false}, {"provincia": "zaragoza", "tipo": "CEIP", "solicitudes": 34, "coord": "41.633074, -0.873851", "oferta": 44, "diferencia": 10, "label": "CEIP MAR\u00cdA MOLINER (ZARAGOZA)", "estado": true}, {"provincia": "zaragoza", "tipo": "CEIP", "solicitudes": 16, "coord": "41.685939, -0.768217", "oferta": 22, "diferencia": 6, "label": "CEIP MARIANO CASTILLO (VILLAMAYOR DE GALLEGO)", "estado": true}, {"provincia": "zaragoza", "tipo": "CEIP", "solicitudes": 59, "coord": "41.659517, -0.863937", "oferta": 66, "diferencia": 7, "label": "CEIP MARIE CURIE (ZARAGOZA)", "estado": true}, {"provincia": "zaragoza", "tipo": "CEIP", "solicitudes": 62, "coord": "41.710241, -0.999391", "oferta": 66, "diferencia": 4, "label": "CEIP MIGUEL ARTAZOS TAM\u00c9 (UTEBO)", "estado": true}, {"provincia": "zaragoza", "tipo": "CEIP", "solicitudes": 41, "coord": "41.641593, -0.877277", "oferta": 75, "diferencia": 34, "label": "CEIP MIRAFLORES (ZARAGOZA)", "estado": true}, {"provincia": "zaragoza", "tipo": "CEIP", "solicitudes": 59, "coord": "41.656325, -0.932817", "oferta": 66, "diferencia": 7, "label": "CEIP MIRALBUENO (ZARAGOZA)", "estado": true}, {"provincia": "zaragoza", "tipo": "CEIP", "solicitudes": 34, "coord": "41.906081, -1.721421", "oferta": 42, "diferencia": 8, "label": "CEIP MONCAYO (TARAZONA)", "estado": true}, {"provincia": "zaragoza", "tipo": "CEIP", "solicitudes": 44, "coord": "41.653299, -0.913377", "oferta": 66, "diferencia": 22, "label": "CEIP MONSALUD (ZARAGOZA)", "estado": true}, {"provincia": "zaragoza", "tipo": "CEIP", "solicitudes": 95, "coord": "41.627899, -0.932397", "oferta": 75, "diferencia": -20, "label": "CEIP MONTECANAL (ZARAGOZA)", "estado": false}, {"provincia": "zaragoza", "tipo": "CEIP", "solicitudes": 11, "coord": "41.474618, -1.372181", "oferta": 21, "diferencia": 10, "label": "CEIP NERT\u00d3BRIGA (ALMUNIA DE DO\u00d1A GODINA (LA))", "estado": true}, {"provincia": "zaragoza", "tipo": "CPRI", "solicitudes": 16, "coord": "41.638013, -0.886406", "oferta": 25, "diferencia": 9, "label": "CPRI NTRA. SRA. DE LA MERCED (ZARAGOZA)", "estado": true}, {"provincia": "zaragoza", "tipo": "CPRI", "solicitudes": 16, "coord": "42.123474, -1.140814", "oferta": 21, "diferencia": 5, "label": "CPRI NTRA. SRA. DE LAS MERCEDES (EJEA DE LOS CABALLEROS)", "estado": true}, {"provincia": "zaragoza", "tipo": "CPRI", "solicitudes": 63, "coord": "41.645649, -0.881106", "oferta": 75, "diferencia": 12, "label": "CPRI NTRA. SRA. DEL CARMEN (ZARAGOZA)", "estado": true}, {"provincia": "zaragoza", "tipo": "CPRI", "solicitudes": 22, "coord": "41.656094, -0.891331", "oferta": 21, "diferencia": -1, "label": "CPRI NTRA. SRA. DEL CARMEN Y SAN JOS\u00c9 (ZARAGOZA)", "estado": false}, {"provincia": "zaragoza", "tipo": "CPRI", "solicitudes": 17, "coord": "41.77228, -1.124615", "oferta": 21, "diferencia": 4, "label": "CPRI NTRA. SRA DEL CASTILLO (ALAGON)", "estado": true}, {"provincia": "zaragoza", "tipo": "CPRI", "solicitudes": 24, "coord": "41.901509, -1.723487", "oferta": 21, "diferencia": -3, "label": "CPRI NTRA. SRA. DEL PILAR (TARAZONA)", "estado": false}, {"provincia": "zaragoza", "tipo": "CPRI", "solicitudes": 16, "coord": "41.871654, -0.792327", "oferta": 21, "diferencia": 5, "label": "CPRI NUESTRA SE\u00d1ORA DEL PILAR (ZUERA)", "estado": true}, {"provincia": "zaragoza", "tipo": "CPRI", "solicitudes": 90, "coord": "41.646462, -0.860012", "oferta": 110, "diferencia": 20, "label": "CPRI OBRA DIOCESANA SANTO DOMINGO DE SILOS (ZARAGOZA)", "estado": true}, {"provincia": "zaragoza", "tipo": "CEIP", "solicitudes": 79, "coord": "41.704491, -0.995238", "oferta": 66, "diferencia": -13, "label": "CEIP OCTAVUS (UTEBO)", "estado": false}, {"provincia": "zaragoza", "tipo": "CEIP", "solicitudes": 37, "coord": "41.867073, -0.788441", "oferta": 42, "diferencia": 5, "label": "CEIP OD\u00d3N DE BUEN (ZUERA)", "estado": true}, {"provincia": "zaragoza", "tipo": "CPRI", "solicitudes": 65, "coord": "41.646852, -0.915482", "oferta": 44, "diferencia": -21, "label": "CPRI PADRE ENRIQUE DE OSS\u00d3 (ZARAGOZA)", "estado": false}, {"provincia": "zaragoza", "tipo": "CEIP", "solicitudes": 39, "coord": "41.702493, -0.998783", "oferta": 44, "diferencia": 5, "label": "CEIP PARQUE EUROPA (UTEBO)", "estado": true}, {"provincia": "zaragoza", "tipo": "CEIP", "solicitudes": 41, "coord": "41.681156, -0.872339", "oferta": 63, "diferencia": 22, "label": "CEIP PARQUE GOYA (ZARAGOZA)", "estado": true}, {"provincia": "zaragoza", "tipo": "CPRI", "solicitudes": 40, "coord": "41.636004, -0.890966", "oferta": 50, "diferencia": 10, "label": "CPRI POMPILIANO (ZARAGOZA)", "estado": true}, {"provincia": "zaragoza", "tipo": "CEIP", "solicitudes": 48, "coord": "41.662573, -0.900051", "oferta": 63, "diferencia": 15, "label": "CEIP PUERTA DE SANCHO (ZARAGOZA)", "estado": true}, {"provincia": "zaragoza", "tipo": "CEIP", "solicitudes": 16, "coord": "41.652459, -0.924027", "oferta": 22, "diferencia": 6, "label": "CEIP RAMIRO SOL\u00c1NS (ZARAGOZA)", "estado": true}, {"provincia": "zaragoza", "tipo": "CEIP", "solicitudes": 52, "coord": "41.625506, -0.881817", "oferta": 75, "diferencia": 23, "label": "CEIP RAM\u00d3N S\u00c1INZ DE VARANDA (ZARAGOZA)", "estado": true}, {"provincia": "zaragoza", "tipo": "CEIP", "solicitudes": 36, "coord": "41.590391, -0.928961", "oferta": 25, "diferencia": -11, "label": "CEIP RAM\u00d3N Y CAJAL (CUARTE DE HUERVA)", "estado": false}, {"provincia": "zaragoza", "tipo": "CEIP", "solicitudes": 4, "coord": "41.487889, -0.529565", "oferta": 21, "diferencia": 17, "label": "CEIP RAM\u00d3N Y CAJAL (PINA DE EBRO)", "estado": true}, {"provincia": "zaragoza", "tipo": "CEIP", "solicitudes": 20, "coord": "41.644029, -0.901522", "oferta": 50, "diferencia": 30, "label": "CEIP RECARTE Y ORNAT (ZARAGOZA)", "estado": true}, {"provincia": "zaragoza", "tipo": "CEIP", "solicitudes": 43, "coord": "42.128487, -1.130205", "oferta": 42, "diferencia": -1, "label": "CEIP RECTOR MAM\u00c9S ESPERAB\u00c9 (EJEA DE LOS CABALLEROS)", "estado": false}, {"provincia": "zaragoza", "tipo": "CEIP", "solicitudes": 31, "coord": "41.631893, -0.757091", "oferta": 42, "diferencia": 11, "label": "CEIP REINO DE ARAG\u00d3N (PUEBLA DE ALFINDEN (LA))", "estado": true}, {"provincia": "zaragoza", "tipo": "CEIP", "solicitudes": 21, "coord": "41.718776, -1.024599", "oferta": 44, "diferencia": 23, "label": "CEIP RICARDO MUR (CASETAS)", "estado": true}, {"provincia": "zaragoza", "tipo": "CEIP", "solicitudes": 36, "coord": "41.669043, -0.894822", "oferta": 63, "diferencia": 27, "label": "CEIP R\u00cdO EBRO (ZARAGOZA)", "estado": true}, {"provincia": "zaragoza", "tipo": "CPRI", "solicitudes": 78, "coord": "41.633738, -0.905856", "oferta": 75, "diferencia": -3, "label": "CPRI ROMAREDA (ZARAGOZA)", "estado": false}, {"provincia": "zaragoza", "tipo": "CEIP", "solicitudes": 74, "coord": "41.634774, -0.940607", "oferta": 100, "diferencia": 26, "label": "CEIP ROSALES DEL CANAL (ZARAGOZA)", "estado": true}, {"provincia": "zaragoza", "tipo": "CPRI", "solicitudes": 11, "coord": "41.905878, -1.728544", "oferta": 21, "diferencia": 10, "label": "CPRI SAGRADA FAMILIA (TARAZONA)", "estado": true}, {"provincia": "zaragoza", "tipo": "CPRI", "solicitudes": 51, "coord": "41.625961, -0.907888", "oferta": 50, "diferencia": -1, "label": "CPRI SAGRADA FAMILIA (ZARAGOZA)", "estado": false}, {"provincia": "zaragoza", "tipo": "CPRI", "solicitudes": 82, "coord": "41.646867, -0.878134", "oferta": 75, "diferencia": -7, "label": "CPRI SAGRADO CORAZ\u00d3N (ZARAGOZA)", "estado": false}, {"provincia": "zaragoza", "tipo": "CPRI", "solicitudes": 96, "coord": "41.671563, -0.882797", "oferta": 84, "diferencia": -12, "label": "CPRI SAGRADO CORAZ\u00d3N DE JES\u00daS (ZARAGOZA)", "estado": false}, {"provincia": "zaragoza", "tipo": "CPRI", "solicitudes": 76, "coord": "41.63754, -0.909847", "oferta": 75, "diferencia": -1, "label": "CPRI SAGRADO CORAZ\u00d3N-MONCAYO (ZARAGOZA)", "estado": false}, {"provincia": "zaragoza", "tipo": "CPRI", "solicitudes": 74, "coord": "41.644635, -0.903298", "oferta": 44, "diferencia": -30, "label": "CPRI SALESIANO NTRA. SRA.DEL PILAR (ZARAGOZA)", "estado": false}, {"provincia": "zaragoza", "tipo": "CEIP", "solicitudes": 6, "coord": "41.902414, -1.720612", "oferta": 21, "diferencia": 15, "label": "CEIP SALVADOR MINGUIJ\u00d3N (CALATAYUD)", "estado": true}, {"provincia": "zaragoza", "tipo": "CPRI", "solicitudes": 91, "coord": "41.641267, -0.881761", "oferta": 75, "diferencia": -16, "label": "CPRI SAN AGUST\u00cdN (ZARAGOZA)", "estado": false}, {"provincia": "zaragoza", "tipo": "CPRI", "solicitudes": 34, "coord": "41.634271, -0.886748", "oferta": 50, "diferencia": 16, "label": "CPRI SAN ANTONIO DE PADUA (ZARAGOZA)", "estado": true}, {"provincia": "zaragoza", "tipo": "CEIP", "solicitudes": 9, "coord": "41.668557, -0.873632", "oferta": 42, "diferencia": 33, "label": "CEIP SAN BRAULIO (ZARAGOZA)", "estado": true}, {"provincia": "zaragoza", "tipo": "CPRI", "solicitudes": 28, "coord": "41.872479, -0.755411", "oferta": 21, "diferencia": -7, "label": "CPRI SAN GABRIEL (ZUERA)", "estado": false}, {"provincia": "zaragoza", "tipo": "CEIP", "solicitudes": 106, "coord": "41.614995, -0.92591", "oferta": 75, "diferencia": -31, "label": "CEIP SAN JORGE (ZARAGOZA)", "estado": false}, {"provincia": "zaragoza", "tipo": "CEIP", "solicitudes": 13, "coord": "41.639189, -0.878376", "oferta": 25, "diferencia": 12, "label": "CEIP SAN JOS\u00c9 DE CALASANZ (ZARAGOZA)", "estado": true}, {"provincia": "zaragoza", "tipo": "CEIP", "solicitudes": 27, "coord": "41.534892, -0.999728", "oferta": 42, "diferencia": 15, "label": "CEIP SAN ROQUE (MARIA DE HUERVA)", "estado": true}, {"provincia": "zaragoza", "tipo": "CPRI", "solicitudes": 42, "coord": "41.653776, -0.875114", "oferta": 44, "diferencia": 2, "label": "CPRI SAN VICENTE DE PA\u00daL (ZARAGOZA)", "estado": true}, {"provincia": "zaragoza", "tipo": "CPRI", "solicitudes": 8, "coord": "41.833309, -1.534824", "oferta": 21, "diferencia": 13, "label": "CPRI SANTA ANA (BORJA)", "estado": true}, {"provincia": "zaragoza", "tipo": "CPRI", "solicitudes": 51, "coord": "41.350551, -1.639177", "oferta": 42, "diferencia": -9, "label": "CPRI SANTA ANA (CALATAYUD)", "estado": false}, {"provincia": "zaragoza", "tipo": "CPRI", "solicitudes": 17, "coord": "41.238088, -0.042015", "oferta": 21, "diferencia": 4, "label": "CPRI SANTA ANA (CASPE)", "estado": true}, {"provincia": "zaragoza", "tipo": "CPRI", "solicitudes": 86, "coord": "41.628708, -0.871074", "oferta": 66, "diferencia": -20, "label": "CPRI SANTA ANA (ZARAGOZA)", "estado": false}, {"provincia": "zaragoza", "tipo": "CPRI", "solicitudes": 44, "coord": "41.636263, -0.925604", "oferta": 44, "diferencia": 0, "label": "CPRI SANTA MAGDALENA SOF\u00cdA (ZARAGOZA)", "estado": true}, {"provincia": "zaragoza", "tipo": "CPRI", "solicitudes": 11, "coord": "41.490718, -0.527099", "oferta": 21, "diferencia": 10, "label": "CPRI SANTA MAR\u00cdA DE LA ESPERANZA (PINA DE EBRO)", "estado": true}, {"provincia": "zaragoza", "tipo": "CPRI", "solicitudes": 88, "coord": "41.626279, -0.900544", "oferta": 100, "diferencia": 12, "label": "CPRI SANTA MAR\u00cdA DEL PILAR (ZARAGOZA)", "estado": true}, {"provincia": "zaragoza", "tipo": "CPRI", "solicitudes": 12, "coord": "41.644198, -0.905012", "oferta": 22, "diferencia": 10, "label": "CPRI SANTA MAR\u00cdA REINA (ZARAGOZA)", "estado": true}, {"provincia": "zaragoza", "tipo": "CPRI", "solicitudes": 40, "coord": "41.651483, -0.883786", "oferta": 50, "diferencia": 10, "label": "CPRI SANTA ROSA (ZARAGOZA)", "estado": true}, {"provincia": "zaragoza", "tipo": "CEIP", "solicitudes": 12, "coord": "41.65776, -0.884998", "oferta": 21, "diferencia": 9, "label": "CEIP SANTO DOMINGO (ZARAGOZA)", "estado": true}, {"provincia": "zaragoza", "tipo": "CEIP", "solicitudes": 26, "coord": "41.653626, -0.870856", "oferta": 44, "diferencia": 18, "label": "CEIP TENER\u00cdAS (ZARAGOZA)", "estado": true}, {"provincia": "zaragoza", "tipo": "CPRI", "solicitudes": 78, "coord": "41.674403, -0.960046", "oferta": 66, "diferencia": -12, "label": "CPRI TERESIANO DEL PILAR (ZARAGOZA)", "estado": false}, {"provincia": "zaragoza", "tipo": "CEIP", "solicitudes": 40, "coord": "41.662586, -0.875318", "oferta": 44, "diferencia": 4, "label": "CEIP T\u00cdO JORGE (ZARAGOZA)", "estado": true}, {"provincia": "zaragoza", "tipo": "CEIP", "solicitudes": 48, "coord": "41.639458, -0.866757", "oferta": 44, "diferencia": -4, "label": "CEIP TOM\u00c1S ALVIRA (ZARAGOZA)", "estado": false}, {"provincia": "zaragoza", "tipo": "CEIP", "solicitudes": 28, "coord": "41.644037, -0.86163", "oferta": 44, "diferencia": 16, "label": "CEIP TORRE RAMONA (ZARAGOZA)", "estado": true}, {"provincia": "zaragoza", "tipo": "CEIP", "solicitudes": 39, "coord": "41.657101, -0.857123", "oferta": 44, "diferencia": 5, "label": "CEIP VADORREY-LES ALL\u00c9ES (ZARAGOZA)", "estado": true}, {"provincia": "zaragoza", "tipo": "CEIP", "solicitudes": 55, "coord": "41.542528, -0.998414", "oferta": 42, "diferencia": -13, "label": "CEIP VAL DE LA ATALAYA (MARIA DE HUERVA)", "estado": false}, {"provincia": "zaragoza", "tipo": "CEIP", "solicitudes": 105, "coord": "41.623872, -0.916836", "oferta": 75, "diferencia": -30, "label": "CEIP VALDESPARTERA (ZARAGOZA)", "estado": false}, {"provincia": "zaragoza", "tipo": "CEIP", "solicitudes": 99, "coord": "41.6267417,-0.9344003", "oferta": 100, "diferencia": 1, "label": "CEIP VALDESPARTERA III (ZARAGOZA)", "estado": true}, {"provincia": "zaragoza", "tipo": "CPRI", "solicitudes": 9, "coord": "41.632909, -0.886549", "oferta": 25, "diferencia": 16, "label": "CPRI VILLA CRUZ (ZARAGOZA)", "estado": true}, {"provincia": "zaragoza", "tipo": "CPRI", "solicitudes": 17, "coord": "41.632074, -0.914992", "oferta": 25, "diferencia": 8, "label": "CPRI VIRGEN DE GUADALUPE (ZARAGOZA)", "estado": true}, {"provincia": "zaragoza", "tipo": "CEIP", "solicitudes": 39, "coord": "41.677064, -0.877718", "oferta": 63, "diferencia": 24, "label": "CEIP ZALFONADA (ZARAGOZA)", "estado": true}, {"provincia": "zaragoza", "tipo": "CEIP", "solicitudes": 83, "coord": "41.635556, -0.947701", "oferta": 75, "diferencia": -8, "label": "CEIP ZARAGOZA SUR (ZARAGOZA)", "estado": false}, {"provincia": "huesca", "tipo": "CEIP", "solicitudes": 34, "coord": "42.13049, -0.417908", "oferta": 44, "diferencia": 10, "label": "CEIP ALCORAZ (HUESCA)", "estado": true}, {"provincia": "huesca", "tipo": "CEIP", "solicitudes": 37, "coord": "42.032941, 0.131694", "oferta": 44, "diferencia": 7, "label": "CEIP ALTO ARAG\u00d3N (BARBASTRO)", "estado": true}, {"provincia": "huesca", "tipo": "CEIP", "solicitudes": 40, "coord": "41.914316, 0.192474", "oferta": 44, "diferencia": 4, "label": "CEIP ARAG\u00d3N (MONZON)", "estado": true}, {"provincia": "huesca", "tipo": "CEIP", "solicitudes": 24, "coord": "42.138563, -0.411667", "oferta": 44, "diferencia": 20, "label": "CEIP EL PARQUE (HUESCA)", "estado": true}, {"provincia": "huesca", "tipo": "CPRI", "solicitudes": 48, "coord": "42.565103, -0.552342", "oferta": 66, "diferencia": 18, "label": "CPRI ESCUELAS P\u00cdAS (JACA)", "estado": true}, {"provincia": "huesca", "tipo": "CEIP", "solicitudes": 35, "coord": "", "oferta": 22, "diferencia": -13, "label": "CEIP FRAGA III (FRAGA)", "estado": false}, {"provincia": "huesca", "tipo": "CEIP", "solicitudes": 44, "coord": "41.912177, 0.192884", "oferta": 44, "diferencia": 0, "label": "CEIP JOAQU\u00cdN COSTA (MONZON)", "estado": true}, {"provincia": "huesca", "tipo": "CEIP", "solicitudes": 48, "coord": "42.140841, -0.419219", "oferta": 66, "diferencia": 18, "label": "CEIP JUAN XXIII (HUESCA)", "estado": true}, {"provincia": "huesca", "tipo": "CEIP", "solicitudes": 26, "coord": "42.032985, 0.121554", "oferta": 44, "diferencia": 18, "label": "CEIP LA MERCED (BARBASTRO)", "estado": true}, {"provincia": "huesca", "tipo": "CEIP", "solicitudes": 34, "coord": "41.519164, 0.350948", "oferta": 44, "diferencia": 10, "label": "CEIP MIGUEL SERVET (FRAGA)", "estado": true}, {"provincia": "huesca", "tipo": "CPRI", "solicitudes": 12, "coord": "41.914533, 0.193516", "oferta": 22, "diferencia": 10, "label": "CPRI MINTE (MONZON)", "estado": true}, {"provincia": "huesca", "tipo": "CEIP", "solicitudes": 13, "coord": "42.576042, -0.544056", "oferta": 22, "diferencia": 9, "label": "CEIP MONTE OROEL (JACA)", "estado": true}, {"provincia": "huesca", "tipo": "CEIP", "solicitudes": 34, "coord": "42.522266, -0.366506", "oferta": 44, "diferencia": 10, "label": "CEIP MONTECORONA (SABI\u00d1ANIGO)", "estado": true}, {"provincia": "huesca", "tipo": "CEIP", "solicitudes": 37, "coord": "41.906682, 0.186445", "oferta": 22, "diferencia": -15, "label": "CEIP MONZ\u00d3N III (MONZON)", "estado": false}, {"provincia": "huesca", "tipo": "CEIP", "solicitudes": 41, "coord": "42.034424, 0.129671", "oferta": 44, "diferencia": 3, "label": "CEIP PEDRO I (BARBASTRO)", "estado": true}, {"provincia": "huesca", "tipo": "CEIP", "solicitudes": 81, "coord": "42.129691, -0.408232", "oferta": 66, "diferencia": -15, "label": "CEIP PEDRO J. RUBIO (HUESCA)", "estado": false}, {"provincia": "huesca", "tipo": "CEIP", "solicitudes": 39, "coord": "42.142132, -0.39668", "oferta": 40, "diferencia": 1, "label": "CEIP P\u00cdO XII (HUESCA)", "estado": true}, {"provincia": "huesca", "tipo": "CEIP", "solicitudes": 62, "coord": "42.130514, -0.401585", "oferta": 66, "diferencia": 4, "label": "CEIP PIRINEOS-PYR\u00c9N\u00c9ES (HUESCA)", "estado": true}, {"provincia": "huesca", "tipo": "CEIP", "solicitudes": 24, "coord": "42.502352, -0.361484", "oferta": 22, "diferencia": -2, "label": "CEIP PUENTE SARDAS (SABI\u00d1ANIGO)", "estado": false}, {"provincia": "huesca", "tipo": "CPRI", "solicitudes": 49, "coord": "42.142304, -0.411805", "oferta": 44, "diferencia": -5, "label": "CPRI SAN BERNARDO (HUESCA)", "estado": false}, {"provincia": "huesca", "tipo": "CPRI", "solicitudes": 27, "coord": "42.036629, 0.123766", "oferta": 22, "diferencia": -5, "label": "CPRI SAN JOS\u00c9 DE CALASANZ (BARBASTRO)", "estado": false}, {"provincia": "huesca", "tipo": "CEIP", "solicitudes": 47, "coord": "41.523043, 0.341532", "oferta": 44, "diferencia": -3, "label": "CEIP SAN JOS\u00c9 DE CALASANZ (FRAGA)", "estado": false}, {"provincia": "huesca", "tipo": "CEIP", "solicitudes": 56, "coord": "42.56766, -0.554639", "oferta": 66, "diferencia": 10, "label": "CEIP SAN JUAN DE LA PE\u00d1A (JACA)", "estado": true}, {"provincia": "huesca", "tipo": "CPRI", "solicitudes": 39, "coord": "42.140015, -0.414192", "oferta": 44, "diferencia": 5, "label": "CPRI SAN VIATOR (HUESCA)", "estado": true}, {"provincia": "huesca", "tipo": "CEIP", "solicitudes": 31, "coord": "42.141459, -0.407364", "oferta": 44, "diferencia": 13, "label": "CEIP SAN VICENTE (HUESCA)", "estado": true}, {"provincia": "huesca", "tipo": "CPRI", "solicitudes": 18, "coord": "42.033204, 0.119075", "oferta": 22, "diferencia": 4, "label": "CPRI SAN VICENTE DE PA\u00daL (BARBASTRO)", "estado": true}, {"provincia": "huesca", "tipo": "CEIP", "solicitudes": 59, "coord": "42.135555, -0.404584", "oferta": 66, "diferencia": 7, "label": "CEIP SANCHO RAM\u00cdREZ (HUESCA)", "estado": true}, {"provincia": "huesca", "tipo": "CPRI", "solicitudes": 48, "coord": "41.526943, 0.33591", "oferta": 44, "diferencia": -4, "label": "CPRI SANTA ANA (FRAGA)", "estado": false}, {"provincia": "huesca", "tipo": "CPRI", "solicitudes": 49, "coord": "42.139553, -0.410684", "oferta": 44, "diferencia": -5, "label": "CPRI SANTA ANA (HUESCA)", "estado": false}, {"provincia": "huesca", "tipo": "CPRI", "solicitudes": 56, "coord": "41.909377, 0.187996", "oferta": 44, "diferencia": -12, "label": "CPRI SANTA ANA (MONZON)", "estado": false}, {"provincia": "huesca", "tipo": "CPRI", "solicitudes": 13, "coord": "42.519875, -0.364329", "oferta": 22, "diferencia": 9, "label": "CPRI SANTA ANA (SABI\u00d1ANIGO)", "estado": true}, {"provincia": "huesca", "tipo": "CPRI", "solicitudes": 46, "coord": "42.142951, -0.414784", "oferta": 44, "diferencia": -2, "label": "CPRI SANTA ROSA-ALTOARAG\u00d3N (HUESCA)", "estado": false}, {"provincia": "huesca", "tipo": "CEIP", "solicitudes": 69, "coord": "41.842911, 0.298658", "oferta": 66, "diferencia": -3, "label": "CEIP V\u00cdCTOR MENDOZA MENDOZA (BINEFAR)", "estado": false}, {"provincia": "huesca", "tipo": "CPRI", "solicitudes": 32, "coord": "41.850232, 0.296405", "oferta": 22, "diferencia": -10, "label": "CPRI VIRGEN DEL ROMERAL (BINEFAR)", "estado": false}, {"provincia": "teruel", "tipo": "CEIP", "solicitudes": 54, "coord": "41.049273, -0.125415", "oferta": 66, "diferencia": 12, "label": "CEIP EMILIO D\u00cdAZ (ALCA\u00d1IZ)", "estado": true}, {"provincia": "teruel", "tipo": "CEIP", "solicitudes": 51, "coord": "40.336604, -1.107012", "oferta": 66, "diferencia": 15, "label": "CEIP ENSANCHE (TERUEL)", "estado": true}, {"provincia": "teruel", "tipo": "CEIP", "solicitudes": 29, "coord": "41.048594, -0.130195", "oferta": 22, "diferencia": -7, "label": "CEIP JUAN LORENZO PALMIRENO (ALCA\u00d1IZ)", "estado": false}, {"provincia": "teruel", "tipo": "CEIP", "solicitudes": 40, "coord": "40.974559, -0.448783", "oferta": 44, "diferencia": 4, "label": "CEIP JUAN RAM\u00d3N ALEGRE (ANDORRA)", "estado": true}, {"provincia": "teruel", "tipo": "CEIP", "solicitudes": 33, "coord": "41.050056, -0.139186", "oferta": 44, "diferencia": 11, "label": "CEIP JUAN SOBRARIAS (ALCA\u00d1IZ)", "estado": true}, {"provincia": "teruel", "tipo": "CEIP", "solicitudes": 82, "coord": "40.329047, -1.095607", "oferta": 66, "diferencia": -16, "label": "CEIP LA FUENFRESCA (TERUEL)", "estado": false}, {"provincia": "teruel", "tipo": "CPRI", "solicitudes": 22, "coord": "41.051436, -0.130893", "oferta": 22, "diferencia": 0, "label": "CPRI LA INMACULADA (ALCA\u00d1IZ)", "estado": true}, {"provincia": "teruel", "tipo": "CPRI", "solicitudes": 14, "coord": "40.340096, -1.105797", "oferta": 18, "diferencia": 4, "label": "CPRI LA PUR\u00cdSIMA Y SANTOS M\u00c1RTIRES (TERUEL)", "estado": true}, {"provincia": "teruel", "tipo": "CPRI", "solicitudes": 46, "coord": "40.33257, -1.099986", "oferta": 44, "diferencia": -2, "label": "CPRI LA SALLE-SAN JOS\u00c9 (TERUEL)", "estado": false}, {"provincia": "teruel", "tipo": "CEIP", "solicitudes": 50, "coord": "40.352816, -1.109244", "oferta": 66, "diferencia": 16, "label": "CEIP LAS ANEJAS (TERUEL)", "estado": true}, {"provincia": "teruel", "tipo": "CPRI", "solicitudes": 38, "coord": "40.351995, -1.119398", "oferta": 44, "diferencia": 6, "label": "CPRI LAS VI\u00d1AS (TERUEL)", "estado": true}, {"provincia": "teruel", "tipo": "CEIP", "solicitudes": 31, "coord": "40.977588, -0.459257", "oferta": 44, "diferencia": 13, "label": "CEIP MANUEL FRANCO ROYO (ANDORRA)", "estado": true}, {"provincia": "teruel", "tipo": "CEIP", "solicitudes": 36, "coord": "40.341507, -1.103128", "oferta": 18, "diferencia": -18, "label": "CEIP MIGUEL VALL\u00c9S (TERUEL)", "estado": false}, {"provincia": "teruel", "tipo": "CEIP", "solicitudes": 15, "coord": "40.34359, -1.109271", "oferta": 18, "diferencia": 3, "label": "CEIP PIERRES VEDEL (TERUEL)", "estado": true}, {"provincia": "teruel", "tipo": "CPRI", "solicitudes": 16, "coord": "41.049989, -0.132154", "oferta": 22, "diferencia": 6, "label": "CPRI SAN VALERO (ALCA\u00d1IZ)", "estado": true}, {"provincia": "teruel", "tipo": "CPRI", "solicitudes": 10, "coord": "40.333383, -1.108403", "oferta": 22, "diferencia": 12, "label": "CPRI VICTORIA D\u00cdEZ (TERUEL)", "estado": true}]}